astrosql/__init__.py
astrosql/apass.py
astrosql/astrosql.py
astrosql/config.py
astrosql/deprecated/__init__.py
astrosql/deprecated/argparser.py
astrosql/deprecated/calibration.py
astrosql/deprecated/command_line.py
astrosql/deprecated/config.yml
astrosql/deprecated/import_data.py
astrosql/deprecated/peeweedb.py
astrosql/deprecated/query.py
astrosql/deprecated/update.py
astrosql/deprecated/writer.py
astrosql/deprecated/zaphot_add_one_image_to_db.py
astrosql/deprecated/zaphot_get_one_image_from_db.py
astrosql/sqlconnector.py
astrosql-1.0.1.dist-info/LICENSE
astrosql-1.0.1.dist-info/WHEEL
astrosql-1.0.1.dist-info/METADATA
astrosql-1.0.1.dist-info/RECORD
